<?xml version="1.0" encoding="UTF-8" standalone="yes"?>
<w:document xmlns:wpc="http://schemas.microsoft.com/office/word/2010/wordprocessingCanvas" xmlns:mc="http://schemas.openxmlformats.org/markup-compatibility/2006" xmlns:o="urn:schemas-microsoft-com:office:office" xmlns:r="http://schemas.openxmlformats.org/officeDocument/2006/relationships" xmlns:m="http://schemas.openxmlformats.org/officeDocument/2006/math" xmlns:v="urn:schemas-microsoft-com:vml" xmlns:wp14="http://schemas.microsoft.com/office/word/2010/wordprocessingDrawing" xmlns:wp="http://schemas.openxmlformats.org/drawingml/2006/wordprocessingDrawing" xmlns:w10="urn:schemas-microsoft-com:office:word" xmlns:w="http://schemas.openxmlformats.org/wordprocessingml/2006/main" xmlns:w14="http://schemas.microsoft.com/office/word/2010/wordml" xmlns:w15="http://schemas.microsoft.com/office/word/2012/wordml" xmlns:wpg="http://schemas.microsoft.com/office/word/2010/wordprocessingGroup" xmlns:wpi="http://schemas.microsoft.com/office/word/2010/wordprocessingInk" xmlns:wne="http://schemas.microsoft.com/office/word/2006/wordml" xmlns:wps="http://schemas.microsoft.com/office/word/2010/wordprocessingShape" mc:Ignorable="w14 w15 wp14"><w:body><w:p w:rsidR="002D05E5" w:rsidRDefault="002D05E5"><w:pPr><w:rPr><w:rStyle w:val="storytitle1"/><w:rFonts w:hint="eastAsia"/></w:rPr></w:pPr><w:bookmarkStart w:id="0" w:name="_GoBack"/><w:bookmarkEnd w:id="0"/><w:r><w:rPr><w:rStyle w:val="storytitle1"/></w:rPr><w:t>以弘揚憲法、厲行法治</w:t></w:r><w:r><w:rPr><w:rStyle w:val="storytitle1"/></w:rPr><w:t>---------</w:t></w:r><w:r><w:rPr><w:rStyle w:val="storytitle1"/></w:rPr><w:t>實踐</w:t></w:r><w:r><w:rPr><w:rStyle w:val="storytitle1"/></w:rPr><w:t xml:space="preserve"> </w:t></w:r><w:r><w:rPr><w:rStyle w:val="storytitle1"/></w:rPr><w:t>蔣公遺訓</w:t></w:r></w:p><w:p w:rsidR="002D05E5" w:rsidRDefault="002D05E5"><w:pPr><w:rPr><w:rStyle w:val="storytitle1"/><w:rFonts w:hint="eastAsia"/></w:rPr></w:pPr></w:p><w:p w:rsidR="002D05E5" w:rsidRDefault="002D05E5" w:rsidP="002D05E5"><w:pPr><w:pStyle w:val="NormalWeb"/><w:spacing w:line="360" w:lineRule="atLeast"/><w:rPr><w:rFonts w:ascii="Verdana" w:hAnsi="Verdana"/><w:color w:val="414141"/><w:sz w:val="22"/><w:szCs w:val="22"/></w:rPr></w:pPr><w:r><w:rPr><w:rFonts w:ascii="Verdana" w:hAnsi="Verdana"/><w:color w:val="414141"/><w:sz w:val="22"/><w:szCs w:val="22"/></w:rPr><w:t>歷史上的人物，多具豐功偉業，但豐功偉業，能否具有歷史上的價值，則要看對國家及社會究作了怎樣的貢獻。中國數千年來的政治傳統，是極權與專制，政治人物能毅然從中脫出，而以民主憲政為依歸，重建社會與政治的新秩序的，真是得未曾有。中</w:t></w:r><w:smartTag w:uri="urn:schemas-microsoft-com:office:smarttags" w:element="PersonName"><w:smartTagPr><w:attr w:name="ProductID" w:val="山"/></w:smartTagPr><w:r><w:rPr><w:rFonts w:ascii="Verdana" w:hAnsi="Verdana"/><w:color w:val="414141"/><w:sz w:val="22"/><w:szCs w:val="22"/></w:rPr><w:t>山</w:t></w:r></w:smartTag><w:r><w:rPr><w:rFonts w:ascii="Verdana" w:hAnsi="Verdana"/><w:color w:val="414141"/><w:sz w:val="22"/><w:szCs w:val="22"/></w:rPr><w:t>先生為民權的先驅，首先點燃民主中國的火炬，但持此火炬，繼續向前，燭照民主與法治的前程的，則是總統蔣公。所以蔣公對國家及社會所作的劃時代的貢獻，還不僅在大家熟知的東征北伐及反共抗俄，而是在這些偉業的最終目的，即民主憲政的建設。蔣公畢生以弘揚民主憲政為職志，雖在國家動盪的時期，仍堅持不移。民國三十七年，政府正併力從事戡亂，當時似有人對憲政的信心動搖，但蔣公則認為戡亂與行憲可以並進。曾說：「我們不因戡亂而延緩憲政的實施，反之，我們正因為要保障憲政的成功，不能不悉力戡亂，以剷除這個建國的障礙與民主的敵人。」民國三十九年，政府已撤退來台，蔣公曾鄭重發表過一個談話，特別強調：「在政治上，我們必須尊重民意，厲行法治。」憲政與法治是人權與民主的實現，我們今日要實踐蔣公的遺訓，當然也必須在這一個基礎上，作更進一步的推進。否則，不僅不能把握蔣公整個思想及力行體系的重心，且易捨本逐末，失去建國的指針。</w:t></w:r><w:r><w:rPr><w:rFonts w:ascii="Verdana" w:hAnsi="Verdana"/><w:color w:val="414141"/><w:sz w:val="22"/><w:szCs w:val="22"/></w:rPr><w:t xml:space="preserve"> </w:t></w:r></w:p><w:p w:rsidR="002D05E5" w:rsidRDefault="002D05E5" w:rsidP="002D05E5"><w:pPr><w:pStyle w:val="NormalWeb"/><w:spacing w:line="360" w:lineRule="atLeast"/><w:rPr><w:rFonts w:ascii="Verdana" w:hAnsi="Verdana"/><w:color w:val="414141"/><w:sz w:val="22"/><w:szCs w:val="22"/></w:rPr></w:pPr><w:r><w:rPr><w:rFonts w:ascii="Verdana" w:hAnsi="Verdana"/><w:color w:val="414141"/><w:sz w:val="22"/><w:szCs w:val="22"/></w:rPr><w:t>所謂憲政決不是一個崇高的理想，也不是一些空洞的口號；法治更不意味著政府統治的憑藉，或政策的實施。實際上，兩者皆出於同一個觀念，即法治本於憲政，憲政來自民權。換句話說，無民權即不產生憲政，無憲政即無真正的法治可言。在中國的傳統政治文化中，人民是被統治的階級，充其量不過是被關愛的對象，並不具有獨立自主的地位。憲政則一反專制的傳統，消極地要保障人民的自由，積極地要促進人民的參與。政府的主要任務，不再是統治，而是服務；人民則成為國家的主權者，不再在被統治下或關愛中，謀求卑微的生活。這種憲政的精神，無可諱言地，仍待我們進一步的發揮。</w:t></w:r><w:r><w:rPr><w:rFonts w:ascii="Verdana" w:hAnsi="Verdana"/><w:color w:val="414141"/><w:sz w:val="22"/><w:szCs w:val="22"/></w:rPr><w:t xml:space="preserve"> </w:t></w:r></w:p><w:p w:rsidR="002D05E5" w:rsidRDefault="002D05E5" w:rsidP="002D05E5"><w:pPr><w:pStyle w:val="NormalWeb"/><w:spacing w:line="360" w:lineRule="atLeast"/><w:rPr><w:rFonts w:ascii="Verdana" w:hAnsi="Verdana"/><w:color w:val="414141"/><w:sz w:val="22"/><w:szCs w:val="22"/></w:rPr></w:pPr><w:r><w:rPr><w:rFonts w:ascii="Verdana" w:hAnsi="Verdana"/><w:color w:val="414141"/><w:sz w:val="22"/><w:szCs w:val="22"/></w:rPr><w:t>首先，我們必須在觀念上將憲法與憲政加以分辨。憲法的制定，本在確立與發揚民權，而為憲政奠定基礎。中</w:t></w:r><w:smartTag w:uri="urn:schemas-microsoft-com:office:smarttags" w:element="PersonName"><w:smartTagPr><w:attr w:name="ProductID" w:val="山"/></w:smartTagPr><w:r><w:rPr><w:rFonts w:ascii="Verdana" w:hAnsi="Verdana"/><w:color w:val="414141"/><w:sz w:val="22"/><w:szCs w:val="22"/></w:rPr><w:t>山</w:t></w:r></w:smartTag><w:r><w:rPr><w:rFonts w:ascii="Verdana" w:hAnsi="Verdana"/><w:color w:val="414141"/><w:sz w:val="22"/><w:szCs w:val="22"/></w:rPr><w:t>先生即明白地指出，憲法是政府的構成法，人民的保障書。如就這一定義，再作深入的觀察，即可知憲法所規定的政府組織，必須建築在民權的保障與民意的監督之上，因非如此，政府即易流於專制。但近年來，我們似乎存有一種模糊的觀念，即憲法的規定，不應對政府的權力多加束縛。也就是說憲法宜配合政府，而不是政府應曲從憲法。在某一些人的潛意識中，對某些國家的任意修改憲法，甚至停止憲政，還可能抱有同情的心理。憲法如修改到不見民權，祇見政府的權威，民意的表露與輿論的監督皆無可能。這樣的憲法，不過是極權統治的工具，而不能作為民權憲政的基石。從法效的觀點看，憲法的效力雖然是最高的，但在憲法之上，仍有至高無上的民權在。憲法能符合及推動民權，才成為憲政，否則，不過是一堆空洞的具文，甚或是專制的張本，而與憲政無涉。因之，我們不能以為制定了憲法，即實施了憲政，這兩者之間有不可逾越的差異在，既不能加以曲解，也不容作自我的陶醉。</w:t></w:r><w:r><w:rPr><w:rFonts w:ascii="Verdana" w:hAnsi="Verdana"/><w:color w:val="414141"/><w:sz w:val="22"/><w:szCs w:val="22"/></w:rPr><w:t xml:space="preserve"> </w:t></w:r></w:p><w:p w:rsidR="002D05E5" w:rsidRDefault="002D05E5" w:rsidP="002D05E5"><w:pPr><w:pStyle w:val="NormalWeb"/><w:spacing w:line="360" w:lineRule="atLeast"/><w:rPr><w:rFonts w:ascii="Verdana" w:hAnsi="Verdana"/><w:color w:val="414141"/><w:sz w:val="22"/><w:szCs w:val="22"/></w:rPr></w:pPr><w:r><w:rPr><w:rFonts w:ascii="Verdana" w:hAnsi="Verdana"/><w:color w:val="414141"/><w:sz w:val="22"/><w:szCs w:val="22"/></w:rPr><w:lastRenderedPageBreak/><w:t>憲政的實施，是否會削弱政府的權威，影響到施政上的大有為？這是另一個值得澄清的觀念。大有為的政府必須以全民的福利為施政的準則，如捨全民的福利，而僅注重少數人或某一階層的既得利益，全民的基礎已失，政府即欲大有為，亦不可得。全民福利的認定，必須根據全民的參與，憲政的目的即在保障及培育人民的自由討論、自由選擇及自由創造的能力，具此能力，再進而參與政府的決策，才可使政府的施政為全民所有，全民所治，全民所享。唯有民有、民治、民享的政府，才配稱為大有為的政府。中</w:t></w:r><w:smartTag w:uri="urn:schemas-microsoft-com:office:smarttags" w:element="PersonName"><w:smartTagPr><w:attr w:name="ProductID" w:val="山"/></w:smartTagPr><w:r><w:rPr><w:rFonts w:ascii="Verdana" w:hAnsi="Verdana"/><w:color w:val="414141"/><w:sz w:val="22"/><w:szCs w:val="22"/></w:rPr><w:t>山</w:t></w:r></w:smartTag><w:r><w:rPr><w:rFonts w:ascii="Verdana" w:hAnsi="Verdana"/><w:color w:val="414141"/><w:sz w:val="22"/><w:szCs w:val="22"/></w:rPr><w:t>先生的萬能政府，在本質上，仍是以政權為治權的根本，如無政權的實施，治權不僅失去制衡，且亦不能代表民意，萬能不免就變成專制了。</w:t></w:r><w:r><w:rPr><w:rFonts w:ascii="Verdana" w:hAnsi="Verdana"/><w:color w:val="414141"/><w:sz w:val="22"/><w:szCs w:val="22"/></w:rPr><w:t xml:space="preserve"> </w:t></w:r></w:p><w:p w:rsidR="002D05E5" w:rsidRDefault="002D05E5" w:rsidP="002D05E5"><w:pPr><w:pStyle w:val="NormalWeb"/><w:spacing w:line="360" w:lineRule="atLeast"/><w:rPr><w:rFonts w:ascii="Verdana" w:hAnsi="Verdana"/><w:color w:val="414141"/><w:sz w:val="22"/><w:szCs w:val="22"/></w:rPr></w:pPr><w:r><w:rPr><w:rFonts w:ascii="Verdana" w:hAnsi="Verdana"/><w:color w:val="414141"/><w:sz w:val="22"/><w:szCs w:val="22"/></w:rPr><w:t>再進一步觀察，憲政下的大有為政府，才是真正具有效能的政府。效能的觀念，不能僅停留在時間的速度上，最重要的還是在決策本身的正確性。正確的政策，往往是符合人民需要與利益的政策，所以憲政的決策程序，常用多數人的公斷代替少數人的專斷，以多數人的監督，策動少數人的執行。這樣的程序，必然是一種開的程序，但開放不見得就是迂緩。將憲政說成迂緩，若非出於誤解，就是畏懼公眾的參與與監督，也就是懼怕政治的開放。迂迴來看，專制的政府並不見得即代表效能，而且在決策上常因私見的偏執，造成不可彌補的錯覺與損失。因此，站在憲政的立場，民意代表的選舉，應具有競爭性，相互之間並應有效的監督。在行政上，公務人員雖多努力從公，但也亟待加強認真服務的觀念。再說從專制權威下解脫的人民，更須要民主文化的洗禮。這一些皆須要當政者作進一步的規劃，而不能將一切脫節的現象歸諸憲政的難行。蔣公對上述的情況，早在民國三十五年即有所感，且曾慨嘆地說到：「如果行使治權的人，不能尊重政權，而侵犯政權，同時行使政權的人，又沒有掌握政權的能力和習慣，則其結果必致完全違背國父創制的精神。</w:t></w:r><w:r><w:rPr><w:rFonts w:ascii="Verdana" w:hAnsi="Verdana"/><w:color w:val="414141"/><w:sz w:val="22"/><w:szCs w:val="22"/></w:rPr><w:t>………</w:t></w:r><w:r><w:rPr><w:rFonts w:ascii="Verdana" w:hAnsi="Verdana"/><w:color w:val="414141"/><w:sz w:val="22"/><w:szCs w:val="22"/></w:rPr><w:t>我相信假如我自己來行使五權憲法，我一定能以國父之心為心，以治權來保護政權，培育政權，使民權充份發展。」</w:t></w:r><w:r><w:rPr><w:rFonts w:ascii="Verdana" w:hAnsi="Verdana"/><w:color w:val="414141"/><w:sz w:val="22"/><w:szCs w:val="22"/></w:rPr><w:t xml:space="preserve"> </w:t></w:r></w:p><w:p w:rsidR="002D05E5" w:rsidRDefault="002D05E5" w:rsidP="002D05E5"><w:pPr><w:pStyle w:val="NormalWeb"/><w:spacing w:line="360" w:lineRule="atLeast"/><w:rPr><w:rFonts w:ascii="Verdana" w:hAnsi="Verdana"/><w:color w:val="414141"/><w:sz w:val="22"/><w:szCs w:val="22"/></w:rPr></w:pPr><w:r><w:rPr><w:rFonts w:ascii="Verdana" w:hAnsi="Verdana"/><w:color w:val="414141"/><w:sz w:val="22"/><w:szCs w:val="22"/></w:rPr><w:t>民主憲政的順利實施，即構成法治遂行的基礎，亦即完美的法治，必須以民權的保障與全民的參與及福利為前提。在這一個前提之下，法律如經過法定的程序而制定，即具有最高的效力：不僅可拘束人民，也同樣可拘束制法者。也就是說，一方面沒有任何人能超越法律的權威，另一方面沒有任何權威，不是由於法律的授與。大致上，中國傳統的政治文化，常使最高的統治者，成為最高的權威者，於是權威在人，而不在法，終形成人存政舉，人亡政息的局面。法律的權威如不受尊重，社會的秩序即難維持，公德心也就連帶無從發揮。我們今日要弘揚憲政，厲行法治，必然在民權的尊重下，努力建立法律的權威，而使社會的安定與正義寄托於法，而非是權威者的實力。各層級的公務人員祇須崇法盡職，服務人民，即為忠貞，不必再以其他任何人為的因素加以考量。人權由憲法保障，進而由法律作進一步的充實。法律對人權的限制，是為了促進全體的秩序，不是消極地制止，而是積極的發揚。在這樣的觀念下，司法獨立，必須嚴格遵守，作為法律尊嚴及社會正義的最後維護。任何對司法審判的干涉，皆足以使法治的精神喪失，而影響到憲政的前途。</w:t></w:r><w:r><w:rPr><w:rFonts w:ascii="Verdana" w:hAnsi="Verdana"/><w:color w:val="414141"/><w:sz w:val="22"/><w:szCs w:val="22"/></w:rPr><w:t xml:space="preserve"> </w:t></w:r></w:p><w:p w:rsidR="002D05E5" w:rsidRDefault="002D05E5" w:rsidP="002D05E5"><w:pPr><w:pStyle w:val="NormalWeb"/><w:spacing w:line="360" w:lineRule="atLeast"/><w:rPr><w:rFonts w:ascii="Verdana" w:hAnsi="Verdana"/><w:color w:val="414141"/><w:sz w:val="22"/><w:szCs w:val="22"/></w:rPr></w:pPr><w:r><w:rPr><w:rFonts w:ascii="Verdana" w:hAnsi="Verdana"/><w:color w:val="414141"/><w:sz w:val="22"/><w:szCs w:val="22"/></w:rPr><w:t>在中國的歷史上，憲政與法治的道路是十分迂迴曲折的，但為了實現自由的生活，反對共產的極權，我們皆必須排除任何困難，致力於憲政與法治文化及制度的建立，以求民主中國的長治永安與光輝燦爛。蔣公曾有一段語重心長的話，值得朝野上下時時警惕：「今日大陸的淪陷，人民遭受了五千年來所未有的浩劫，使我們更加覺得這部民主憲法的可貴，我們可以說，沒有這部民主憲法，就無人民生命的保障，亦就無人民生活的自由。我們要生活得到自由，生命得到保障，就要以生命來保衛我們的憲法，以生命來保衛我們的民主。」【</w:t></w:r><w:smartTag w:uri="urn:schemas-microsoft-com:office:smarttags" w:element="chsdate"><w:smartTagPr><w:attr w:name="IsROCDate" w:val="False"/><w:attr w:name="IsLunarDate" w:val="False"/><w:attr w:name="Day" w:val="31"/><w:attr w:name="Month" w:val="10"/><w:attr w:name="Year" w:val="1975"/></w:smartTagPr><w:r><w:rPr><w:rFonts w:ascii="Verdana" w:hAnsi="Verdana"/><w:color w:val="414141"/><w:sz w:val="22"/><w:szCs w:val="22"/></w:rPr><w:t>1975-10-31</w:t></w:r></w:smartTag><w:r><w:rPr><w:rFonts w:ascii="Verdana" w:hAnsi="Verdana"/><w:color w:val="414141"/><w:sz w:val="22"/><w:szCs w:val="22"/></w:rPr><w:t>/</w:t></w:r><w:r><w:rPr><w:rFonts w:ascii="Verdana" w:hAnsi="Verdana"/><w:color w:val="414141"/><w:sz w:val="22"/><w:szCs w:val="22"/></w:rPr><w:t>聯合報</w:t></w:r><w:r><w:rPr><w:rFonts w:ascii="Verdana" w:hAnsi="Verdana"/><w:color w:val="414141"/><w:sz w:val="22"/><w:szCs w:val="22"/></w:rPr><w:t>/14</w:t></w:r><w:r><w:rPr><w:rFonts w:ascii="Verdana" w:hAnsi="Verdana"/><w:color w:val="414141"/><w:sz w:val="22"/><w:szCs w:val="22"/></w:rPr><w:t>版</w:t></w:r><w:r><w:rPr><w:rFonts w:ascii="Verdana" w:hAnsi="Verdana"/><w:color w:val="414141"/><w:sz w:val="22"/><w:szCs w:val="22"/></w:rPr><w:t>/</w:t></w:r><w:r><w:rPr><w:rFonts w:ascii="Verdana" w:hAnsi="Verdana"/><w:color w:val="414141"/><w:sz w:val="22"/><w:szCs w:val="22"/></w:rPr><w:t>】</w:t></w:r></w:p><w:p w:rsidR="002D05E5" w:rsidRPr="002D05E5" w:rsidRDefault="002D05E5"><w:pPr><w:rPr><w:rFonts w:hint="eastAsia"/></w:rPr></w:pPr></w:p><w:sectPr w:rsidR="002D05E5" w:rsidRPr="002D05E5"><w:pgSz w:w="11906" w:h="16838"/><w:pgMar w:top="1440" w:right="1800" w:bottom="1440" w:left="1800" w:header="851" w:footer="992" w:gutter="0"/><w:cols w:space="425"/><w:docGrid w:type="lines" w:linePitch="360"/></w:sectPr></w:body></w:document>