<?xml version="1.0" encoding="UTF-8" standalone="yes"?>
<w:document xmlns:wpc="http://schemas.microsoft.com/office/word/2010/wordprocessingCanvas" xmlns:mc="http://schemas.openxmlformats.org/markup-compatibility/2006" xmlns:o="urn:schemas-microsoft-com:office:office" xmlns:r="http://schemas.openxmlformats.org/officeDocument/2006/relationships" xmlns:m="http://schemas.openxmlformats.org/officeDocument/2006/math" xmlns:v="urn:schemas-microsoft-com:vml" xmlns:wp14="http://schemas.microsoft.com/office/word/2010/wordprocessingDrawing" xmlns:wp="http://schemas.openxmlformats.org/drawingml/2006/wordprocessingDrawing" xmlns:w10="urn:schemas-microsoft-com:office:word" xmlns:w="http://schemas.openxmlformats.org/wordprocessingml/2006/main" xmlns:w14="http://schemas.microsoft.com/office/word/2010/wordml" xmlns:w15="http://schemas.microsoft.com/office/word/2012/wordml" xmlns:wpg="http://schemas.microsoft.com/office/word/2010/wordprocessingGroup" xmlns:wpi="http://schemas.microsoft.com/office/word/2010/wordprocessingInk" xmlns:wne="http://schemas.microsoft.com/office/word/2006/wordml" xmlns:wps="http://schemas.microsoft.com/office/word/2010/wordprocessingShape" mc:Ignorable="w14 w15 wp14"><w:body><w:p w:rsidR="00BA4FED" w:rsidRDefault="00B611D8" w:rsidP="00EB5A1D"><w:pPr><w:rPr><w:rFonts w:hint="eastAsia"/><w:sz w:val="28"/><w:szCs w:val="28"/></w:rPr></w:pPr><w:bookmarkStart w:id="0" w:name="_GoBack"/><w:bookmarkEnd w:id="0"/><w:r><w:rPr><w:rFonts w:hint="eastAsia"/><w:sz w:val="28"/><w:szCs w:val="28"/></w:rPr><w:t>人間烽火看蘇聯政變</w:t></w:r></w:p><w:p w:rsidR="006362C8" w:rsidRPr="002C2838" w:rsidRDefault="00B611D8" w:rsidP="00EB5A1D"><w:pPr><w:rPr><w:rFonts w:hint="eastAsia"/></w:rPr></w:pPr><w:r><w:rPr><w:rFonts w:hint="eastAsia"/></w:rPr><w:t>李永熾</w:t></w:r></w:p><w:p w:rsidR="00680826" w:rsidRPr="00680826" w:rsidRDefault="00680826" w:rsidP="00976EE4"><w:pPr><w:rPr><w:rFonts w:hint="eastAsia"/></w:rPr></w:pPr></w:p><w:p w:rsidR="00A02081" w:rsidRDefault="00C7340D" w:rsidP="00680826"><w:pPr><w:rPr><w:rFonts w:hint="eastAsia"/></w:rPr></w:pPr><w:r w:rsidRPr="00EB5A1D"><w:rPr><w:rFonts w:hint="eastAsia"/></w:rPr><w:t xml:space="preserve">　</w:t></w:r><w:r w:rsidR="00680826"><w:rPr><w:rFonts w:hint="eastAsia"/></w:rPr><w:t xml:space="preserve">　</w:t></w:r><w:r w:rsidR="000119B0"><w:rPr><w:rFonts w:hint="eastAsia"/></w:rPr><w:t>蘇聯保守派發動政變，罷黜戈巴契夫，僅僅三天，政變就失敗，戈巴契夫復位。在這三天中，台灣報界又像波斯灣戰爭，大幅報導，讓讀者充分滿足了知的欲望。從報導中可以發現一件很有趣的事，波斯灣戰爭中支持哈珊的國家大都支持蘇聯政變集團，如利比亞、巴解，還有伊拉克自己。反哈珊的幾乎都支持戈巴契夫。在這情境下，走資派的戈巴契夫獲得資本主義國家支持，不得軍事強人歡迎，</w:t></w:r><w:r w:rsidR="0059614E"><w:rPr><w:rFonts w:hint="eastAsia"/></w:rPr><w:t>自是理所當然。可是，很可惜，這次戰爭似乎又是走資派贏得勝利，反資的軍事強人落了空。</w:t></w:r></w:p><w:p w:rsidR="00B422BD" w:rsidRDefault="00B422BD" w:rsidP="00B422BD"><w:pPr><w:spacing w:before="180"/><w:rPr><w:rFonts w:hint="eastAsia"/></w:rPr></w:pPr><w:r><w:rPr><w:rFonts w:hint="eastAsia"/></w:rPr><w:t xml:space="preserve">　　</w:t></w:r><w:r w:rsidR="0059614E"><w:rPr><w:rFonts w:hint="eastAsia"/></w:rPr><w:t>戈巴契夫搞改革，不僅喪失東歐的霸權，還使境內的共和國紛紛獨立自主，的確讓統一的大帝國不像統一的帝國；而反政變的葉爾辛不僅是起身</w:t></w:r><w:r w:rsidR="009149ED"><w:rPr><w:rFonts w:hint="eastAsia"/></w:rPr><w:t>街頭運動的激進走資派，更是一個主張獨立自主的野心家。在大帝國意識很強烈的保守派或強人派看來，這兩個人是墮落的象徵，最好從權力寶座上消失。但是，歷史常具反諷性，蘇聯當政的權力者從來都一垮到底，沒有再翻身復位的，戈巴契夫卻創造了歷史。而帮助戈巴契夫創造歷史的竟是街頭運動家葉爾辛。在某些人眼中，人民顯然又被葉爾辛煽動了，然而卻有人說人民的力量來自街頭，可印</w:t></w:r><w:r w:rsidR="00B247DE"><w:rPr><w:rFonts w:hint="eastAsia"/></w:rPr><w:t>證人民主權的正當性；中國第二次天安門事件卻又加以反證。問題出在什麼地方？是民族性？是中國缺乏主權理念？還是沒有葉爾辛這樣敢在最危急時挺身而出的街頭政治人物？</w:t></w:r></w:p><w:p w:rsidR="00B247DE" w:rsidRPr="00EB5A1D" w:rsidRDefault="00B247DE" w:rsidP="00B422BD"><w:pPr><w:spacing w:before="180"/><w:rPr><w:rFonts w:hint="eastAsia"/></w:rPr></w:pPr><w:r><w:rPr><w:rFonts w:hint="eastAsia"/></w:rPr><w:t xml:space="preserve">　　蘇聯政變僅三天就結束，無法讓台灣評論家像波斯灣戰爭那樣各取所欲，暢所欲言。但在這三天中，也許寄望改革甚為殷切，台灣評論家絕大多數都借題發揮批判蘇聯的軍人政變，只有極少數人看出戈氏走資所造成的結果，而採取嚴厲批戈的態度，但戈氏失敗的改革仍能獲得人民支持，的確奇妙。</w:t></w:r></w:p><w:p w:rsidR="006E1F04" w:rsidRPr="00EB5A1D" w:rsidRDefault="006E1F04" w:rsidP="00B422BD"><w:pPr><w:spacing w:before="180"/><w:rPr><w:rFonts w:hint="eastAsia"/></w:rPr></w:pPr><w:r><w:rPr><w:rFonts w:hint="eastAsia"/></w:rPr><w:t>中</w:t></w:r><w:r w:rsidR="00760060"><w:rPr><w:rFonts w:hint="eastAsia"/></w:rPr><w:t>國</w:t></w:r><w:r><w:rPr><w:rFonts w:hint="eastAsia"/></w:rPr><w:t>時</w:t></w:r><w:r w:rsidR="00760060"><w:rPr><w:rFonts w:hint="eastAsia"/></w:rPr><w:t>報</w:t></w:r><w:r><w:rPr><w:rFonts w:hint="eastAsia"/></w:rPr><w:t xml:space="preserve">　</w:t></w:r><w:r w:rsidR="00F879CE"><w:rPr><w:rFonts w:hint="eastAsia"/></w:rPr><w:t>1991</w:t></w:r><w:r w:rsidR="00FF43BB"><w:rPr><w:rFonts w:hint="eastAsia"/></w:rPr><w:t>年</w:t></w:r><w:r w:rsidR="00F879CE"><w:rPr><w:rFonts w:hint="eastAsia"/></w:rPr><w:t>8</w:t></w:r><w:r w:rsidR="00FF43BB"><w:rPr><w:rFonts w:hint="eastAsia"/></w:rPr><w:t>月</w:t></w:r><w:r w:rsidR="00F879CE"><w:rPr><w:rFonts w:hint="eastAsia"/></w:rPr><w:t>24</w:t></w:r><w:r w:rsidR="00FF43BB"><w:rPr><w:rFonts w:hint="eastAsia"/></w:rPr><w:t>日</w:t></w:r></w:p><w:sectPr w:rsidR="006E1F04" w:rsidRPr="00EB5A1D" w:rsidSect="00653732"><w:pgSz w:w="11906" w:h="16838" w:code="9"/><w:pgMar w:top="1440" w:right="1797" w:bottom="1440" w:left="1797" w:header="851" w:footer="992" w:gutter="0"/><w:cols w:space="425"/><w:docGrid w:type="lines" w:linePitch="360" w:charSpace="57241"/></w:sectPr></w:body></w:document>